zipwrap/__init__.py
zipwrap/__main__.py
zipwrap/cli.py
zipwrap/config.py
zipwrap-1.0.2.dist-info/METADATA
zipwrap-1.0.2.dist-info/WHEEL
zipwrap-1.0.2.dist-info/entry_points.txt
zipwrap-1.0.2.dist-info/RECORD
